u0_stitcher/__init__.py
u0_stitcher/errors.py
u0_stitcher/fisheye2Equirectangular.py
u0_stitcher/stitchEasy3.py
u0_stitcher/stitcher.py
u0_stitcher-0.1.6.dist-info/METADATA
u0_stitcher-0.1.6.dist-info/WHEEL
u0_stitcher-0.1.6.dist-info/top_level.txt
u0_stitcher-0.1.6.dist-info/RECORD
