Metadata-Version: 2.1
Name: u0-stitcher
Version: 0.1.6
Summary: stitcher for two fisheye camera
Home-page: https://github.com/u03013112/pano
Author: u03013112
Author-email: u03013112@hotmail.com
Classifier: Development Status :: 3 - Alpha
Classifier: Intended Audience :: Developers
Classifier: License :: OSI Approved :: MIT License
Classifier: Programming Language :: Python :: 3
Classifier: Programming Language :: Python :: 3.6
Classifier: Programming Language :: Python :: 3.7
Classifier: Programming Language :: Python :: 3.8
Classifier: Programming Language :: Python :: 3.9
Requires-Dist: numpy
Requires-Dist: opencv-python
